tests/__init__.py
tests/test_things.py
things/__init__.py
things/api.py
things/conftest.py
things/database.py
things.py-0.0.15.dist-info/LICENSE
things.py-0.0.15.dist-info/METADATA
things.py-0.0.15.dist-info/WHEEL
things.py-0.0.15.dist-info/top_level.txt
things.py-0.0.15.dist-info/RECORD
