Metadata-Version: 2.1
Name: things.py
Version: 0.0.15
Summary: A simple Python 3 library to read your Things app data.
Home-page: https://github.com/thingsapi/things.py
Author: Alexander Willner, Michael B.
Author-email: alex@willner.ws
License: UNKNOWN
Platform: UNKNOWN
Classifier: Development Status :: 3 - Alpha
Classifier: Programming Language :: Python :: 3
Classifier: License :: OSI Approved :: Apache Software License
Classifier: Operating System :: MacOS :: MacOS X
Classifier: Natural Language :: English
Requires-Python: >=3.7
License-File: LICENSE
